README.rst
setup.py
physics_toolbox/__init__.py
physics_toolbox.egg-info/PKG-INFO
physics_toolbox.egg-info/SOURCES.txt
physics_toolbox.egg-info/dependency_links.txt
physics_toolbox.egg-info/top_level.txt